movieparse/__init__.py
movieparse/__main__.py
movieparse/cli.py
movieparse/main.py
movieparse/py.typed
movieparse-0.4.0.dist-info/entry_points.txt
movieparse-0.4.0.dist-info/LICENSE
movieparse-0.4.0.dist-info/WHEEL
movieparse-0.4.0.dist-info/METADATA
movieparse-0.4.0.dist-info/RECORD
