Metadata-Version: 2.1
Name: movieparse
Version: 0.4.0
Summary: Movieparse
Home-page: https://github.com/tilschuenemann/movieparse
License: MIT
Author: Til Schünemann
Author-email: til.schuenemann@mailbox.org
Requires-Python: >=3.10.7,<4.0.0
Classifier: Development Status :: 3 - Alpha
Classifier: License :: OSI Approved :: MIT License
Classifier: Programming Language :: Python :: 3
Classifier: Programming Language :: Python :: 3.11
Requires-Dist: aiohttp (>=3.8.3,<4.0.0)
Requires-Dist: click (>=8.0.1)
Requires-Dist: numpy (>=1.23.5,<2.0.0)
Requires-Dist: pandas (>=1.5.1,<2.0.0)
Requires-Dist: pathlib (>=1.0.1,<2.0.0)
Requires-Dist: tqdm (>=4.64.1,<5.0.0)
Project-URL: Changelog, https://github.com/tilschuenemann/movieparse/releases
Project-URL: Documentation, https://movieparse.readthedocs.io
Project-URL: Repository, https://github.com/tilschuenemann/movieparse
